pipis/__init__.py
pipis/__main__.py
pipis/utils.py
pipis-2.0.0.post2.data/scripts/pipis
pipis-2.0.0.post2.dist-info/LICENSE
pipis-2.0.0.post2.dist-info/METADATA
pipis-2.0.0.post2.dist-info/WHEEL
pipis-2.0.0.post2.dist-info/top_level.txt
pipis-2.0.0.post2.dist-info/RECORD
